main.py
scraper.py
setup.py
Play_Store_Scraper.egg-info/PKG-INFO
Play_Store_Scraper.egg-info/SOURCES.txt
Play_Store_Scraper.egg-info/dependency_links.txt
Play_Store_Scraper.egg-info/entry_points.txt
Play_Store_Scraper.egg-info/requires.txt
Play_Store_Scraper.egg-info/top_level.txt
Play_Store_Scraper.egg-info/zip-safe