Metadata-Version: 1.0
Name: Play-Store-Scraper
Version: 0.0.1
Summary: Scrapes images and description of apps in google play store
Home-page: UNKNOWN
Author: Saurabh AV
Author-email: saurabhav.torres@gmail.com
License: MIT
Keywords: play store scraper
Platform: UNKNOWN
